openai_api_wrapper/__init__.py
openai_api_wrapper/__version__.py
openai_api_wrapper/chatbot.py
openai_api_wrapper/chatbots/__init__.py
openai_api_wrapper/chatbots/basechatbot.py
openai_api_wrapper/chatbots/chatbot.py
openai_api_wrapper/chatbots/chatglm.py
openai_api_wrapper/chatbots/chatglmbot.py
openai_api_wrapper/chatbots/chatgptbot.py
openai_api_wrapper-0.6.0.dist-info/LICENSE
openai_api_wrapper-0.6.0.dist-info/METADATA
openai_api_wrapper-0.6.0.dist-info/WHEEL
openai_api_wrapper-0.6.0.dist-info/top_level.txt
openai_api_wrapper-0.6.0.dist-info/RECORD
