Metadata-Version: 2.1
Name: openai-api-wrapper
Version: 0.6.0
Summary: This Python package provides a comprehensive and efficient wrapper for the OpenAI API, designed to support advanced application development based on ChatGPT.
Home-page: https://gitlab.com/runnable.it/openai-api-wrapper
Author: Jiangwen Su
Author-email: 531045572@qq.com
License: MIT
Classifier: License :: OSI Approved :: MIT License
Classifier: Intended Audience :: Developers
Classifier: Natural Language :: English
Classifier: Operating System :: OS Independent
Classifier: Topic :: Scientific/Engineering :: Artificial Intelligence
Classifier: Programming Language :: Python :: 3 :: Only
Classifier: Programming Language :: Python :: 3.9
Classifier: Programming Language :: Python :: 3.10
Classifier: Programming Language :: Python :: 3.11
License-File: LICENSE
Requires-Dist: openai
